mkbook/__init__.py
mkbook/main.py
mkbook/mkbook.py
mkbook/py.typed
mkbook/fonts/RampartOne-Regular.ttf
mkbook-0.0.4.dist-info/METADATA
mkbook-0.0.4.dist-info/WHEEL
mkbook-0.0.4.dist-info/entry_points.txt
mkbook-0.0.4.dist-info/licenses/LICENSE
mkbook-0.0.4.dist-info/RECORD
