Metadata-Version: 2.4
Name: mkbook
Version: 0.0.4
Summary: Make directory including pictures into a PDF book
Project-URL: Repository, https://github.com/eggplants/mkbook
Author-email: eggplants <w10776e8w@yahoo.co.jp>
License: MIT
License-File: LICENSE
Keywords: conbine,getjump,pdf
Classifier: License :: OSI Approved :: MIT License
Classifier: Programming Language :: Python
Classifier: Programming Language :: Python :: 3 :: Only
Classifier: Programming Language :: Python :: 3.9
Classifier: Programming Language :: Python :: 3.10
Classifier: Programming Language :: Python :: 3.11
Classifier: Programming Language :: Python :: 3.12
Classifier: Programming Language :: Python :: 3.13
Classifier: Programming Language :: Python :: Implementation :: CPython
Classifier: Typing :: Typed
Requires-Python: <4,>=3.9
Requires-Dist: pillow<12,>=11.1
Requires-Dist: reportlab<5,>=4.2.5
Requires-Dist: types-pillow<11,>=10.2.0.20240822
Requires-Dist: types-reportlab<5,>=4.2.5.20241221
